[
  {
    "Algorithm": "MPI-IMM",
    "DiffusionModel": "IC",
    "Epsilon": 0.13,
    "FindMostInfluentialSet": 2.369938e-317,
    "GenerateRRRSets": 2e-05,
    "Input": "/global/cfs/cdirs/m1641/network-data/Binaries/orkut_big_binary.txt",
    "K": 100,
    "L": 1,
    "NumGPUWalkWorkers": 0,
    "NumThreads": 64,
    "NumWalkWorkers": 64,
    "Output": "/global/cfs/cdirs/m1641/network-results/orkut_big/OrkutBig65_streaming.json",
    "Rank": 0,
    "Seeds": [
      425012,
      110,
      392646,
      1467837,
      2262755,
      993600,
      1306113,
      1216775,
      1243675,
      1736824,
      1259949,
      2375420,
      1237032,
      940481,
      1609299,
      1164453,
      1177148,
      440855,
      429902,
      117730,
      967599,
      978309,
      1467963,
      1706571,
      1880179,
      2668162,
      1397339,
      331769,
      1683738,
      1600890,
      1219576,
      1618078,
      906494,
      679382,
      963274,
      1588539,
      2374279,
      2365139,
      441103,
      2558679,
      2696476,
      2410383,
      2687103,
      1256864,
      1938164,
      1968903,
      1187102,
      1880136,
      2588999,
      1464182,
      1202850,
      1159136,
      1968743,
      1124689,
      979582,
      1374313,
      980287,
      430768,
      1377353,
      2589691,
      1724629,
      1563503,
      1842507,
      1283239,
      980288,
      1305703,
      332738,
      349006,
      1487052,
      935765,
      1685182,
      1425562,
      335122,
      1131704,
      1480946,
      1033957,
      1957987,
      1297344,
      957620,
      1067905,
      2257014,
      1453760,
      2227085,
      918206,
      1618856,
      1696519,
      1228288,
      1640151,
      1562448,
      1465178,
      1654151,
      1577829,
      1291142,
      1636438,
      1308209,
      2591064,
      1302338,
      1389869,
      1317184,
      2722712
    ],
    "Theta": 1238614,
    "ThetaEstimation": 221000.584158,
    "ThetaEstimationGenerateRRR": [
      26933.584759,
      31806.678713,
      56880.141023,
      105379.80939,
      37730.403185
    ],
    "ThetaEstimationMostInfluential": [
      3e-05,
      3.1e-05,
      2.9e-05,
      3e-05,
      3e-05
    ],
    "ThetaPrimeDeltas": [
      2430,
      2430,
      4860,
      9719
    ],
    "Total": 258782.949214,
    "WorldSize": 65
  }
]