[
  {
    "Algorithm": "MPI-IMM",
    "DiffusionModel": "IC",
    "Epsilon": 0.13,
    "FindMostInfluentialSet": 6.9529458097809e-310,
    "GenerateRRRSets": 35371.837627,
    "Input": "/global/cfs/cdirs/m1641/network-data/Binaries/friendster_binary.txt",
    "K": 100,
    "L": 1,
    "NumGPUWalkWorkers": 0,
    "NumThreads": 64,
    "NumWalkWorkers": 64,
    "Output": "/global/cfs/cdirs/m1641/network-results/strong_scaling/friendster/m1025_friendster.json",
    "Rank": 0,
    "Seeds": [
      433843,
      2103179,
      1214072,
      176044,
      187307,
      107415,
      7003,
      2805,
      407,
      14218,
      11912,
      17164,
      10387,
      10311,
      13914,
      10845,
      15384,
      14319,
      8026,
      4001,
      5481,
      3266,
      8248,
      16220,
      2714,
      6761,
      1950,
      10837,
      12252,
      42740,
      1189,
      16258,
      13987,
      1029,
      40696,
      3449,
      7801,
      13423,
      11854,
      7912,
      24132,
      7716,
      3027,
      9405,
      5093,
      1530,
      9852,
      11485,
      16096,
      13522
    ],
    "Theta": 303149,
    "ThetaEstimation": 100767.131427,
    "ThetaEstimationGenerateRRR": [
      100766.841016,
      65265.652462
    ],
    "ThetaEstimationMostInfluential": [
      2.1e-05,
      2e-05
    ],
    "ThetaPrimeDeltas": [
      180
    ],
    "Total": 201810.420459,
    "WorldSize": 1025
  }
]